ghidralldb/__init__.py
ghidralldb/arch.py
ghidralldb/commands.py
ghidralldb/hooks.py
ghidralldb/methods.py
ghidralldb/py.typed
ghidralldb/schema.xml
ghidralldb/util.py
ghidralldb-12.0.dist-info/licenses/LICENSE
ghidralldb-12.0.dist-info/METADATA
ghidralldb-12.0.dist-info/WHEEL
ghidralldb-12.0.dist-info/top_level.txt
ghidralldb-12.0.dist-info/RECORD
