Metadata-Version: 2.4
Name: ghidralldb
Version: 12.0
Summary: Ghidra's Plugin for lldb
Author: Ghidra Development Team
Project-URL: Homepage, https://github.com/NationalSecurityAgency/ghidra
Project-URL: Bug Tracker, https://github.com/NationalSecurityAgency/ghidra/issues
Classifier: Programming Language :: Python :: 3
Classifier: License :: OSI Approved :: Apache Software License
Classifier: Operating System :: OS Independent
Requires-Python: >=3.9
License-File: LICENSE
Requires-Dist: ghidratrace==12.0
Dynamic: license-file
